README.md
SimpleWeather.py
setup.py
SimpleWeather.egg-info/PKG-INFO
SimpleWeather.egg-info/SOURCES.txt
SimpleWeather.egg-info/dependency_links.txt
SimpleWeather.egg-info/requires.txt
SimpleWeather.egg-info/top_level.txt