Metadata-Version: 2.1
Name: SimpleWeather
Version: 1.0.3
Summary: 一个简单的天气爬虫，可以获取某个城市简单的天气信息
Home-page: https://github.com/MCTF-Alpha-27/SimpleWeather
Author: Jerry0940
Author-email: j13816180940@139.com
License: MIT
Platform: UNKNOWN
Classifier: Programming Language :: Python :: 3
